[
  [
    {
      "__type__": "cc.Prefab",
      "_name": "LoadingBar",
      "data": {
        "__id__": 1
      }
    },
    {
      "__type__": "cc.Node",
      "_name": "LoadingBar",
      "_children": [
        {
          "__id__": 2
        },
        {
          "__id__": 3
        },
        {
          "__id__": 5
        }
      ],
      "_components": [
        {
          "__type__": "cc.BlockInputEvents",
          "node": {
            "__id__": 1
          }
        },
        {
          "__type__": "6eaf19K3v1LRp152SOh8etD",
          "node": {
            "__id__": 1
          },
          "barRes": {
            "__id__": 9
          },
          "lbTip": {
            "__id__": 4
          }
        }
      ],
      "_prefab": {
        "__type__": "cc.PrefabInfo",
        "root": {
          "__id__": 1
        },
        "asset": {
          "__uuid__": "64jiExftZFbarLd0gJWROg"
        },
        "fileId": "6azqy9SAxIcKtUCZ21/NH/"
      },
      "_contentSize": {
        "__type__": "cc.Size",
        "width": 1280,
        "height": 720
      },
      "_trs": {
        "__type__": "TypedArray",
        "ctor": "Float64Array",
        "array": [
          0,
          0,
          0,
          0,
          0,
          0,
          1,
          1,
          1,
          1
        ]
      }
    },
    {
      "__type__": "cc.Node",
      "_name": "mask",
      "_parent": {
        "__id__": 1
      },
      "_components": [
        {
          "__type__": "cc.Sprite",
          "_name": "mask<Sprite>",
          "node": {
            "__id__": 2
          },
          "_materials": [
            {
              "__uuid__": "ecpdLyjvZBwrvm+cedCcQy"
            }
          ],
          "_spriteFrame": {
            "__uuid__": "a2MjXRFdtLlYQ5ouAFv/+R"
          },
          "_sizeMode": 0
        },
        {
          "__type__": "cc.Widget",
          "node": {
            "__id__": 2
          },
          "_alignFlags": 45,
          "_originalWidth": 1280,
          "_originalHeight": 720
        }
      ],
      "_prefab": {
        "__type__": "cc.PrefabInfo",
        "root": {
          "__id__": 1
        },
        "asset": {
          "__uuid__": "64jiExftZFbarLd0gJWROg"
        },
        "fileId": "0ccPZHFZFEzZNu/o/rCdlO"
      },
      "_opacity": 35,
      "_color": {
        "__type__": "cc.Color"
      },
      "_contentSize": {
        "__type__": "cc.Size",
        "width": 1280,
        "height": 720
      },
      "_trs": {
        "__type__": "TypedArray",
        "ctor": "Float64Array",
        "array": [
          0,
          0,
          0,
          0,
          0,
          0,
          1,
          1,
          1,
          1
        ]
      }
    },
    {
      "__type__": "cc.Node",
      "_name": "lbTxt",
      "_parent": {
        "__id__": 1
      },
      "_components": [
        {
          "__id__": 4
        }
      ],
      "_prefab": {
        "__type__": "cc.PrefabInfo",
        "root": {
          "__id__": 1
        },
        "asset": {
          "__uuid__": "64jiExftZFbarLd0gJWROg"
        },
        "fileId": "4fvf0yahxFwY3pFIGbYegg"
      },
      "_color": {
        "__type__": "cc.Color",
        "r": 254,
        "g": 247,
        "b": 131
      },
      "_contentSize": {
        "__type__": "cc.Size",
        "width": 105,
        "height": 27.72
      },
      "_trs": {
        "__type__": "TypedArray",
        "ctor": "Float64Array",
        "array": [
          0,
          -16.652,
          0,
          0,
          0,
          0,
          1,
          1,
          1,
          1
        ]
      }
    },
    {
      "__type__": "cc.Label",
      "_name": "lbTxt<Label>",
      "node": {
        "__id__": 3
      },
      "_materials": [
        {
          "__uuid__": "ecpdLyjvZBwrvm+cedCcQy"
        }
      ],
      "_useOriginalSize": false,
      "_string": "进入游戏中...",
      "_N$string": "进入游戏中...",
      "_fontSize": 18,
      "_lineHeight": 22,
      "_N$horizontalAlign": 1,
      "_N$verticalAlign": 1
    },
    {
      "__type__": "cc.Node",
      "_name": "barRes",
      "_parent": {
        "__id__": 1
      },
      "_children": [
        {
          "__id__": 6
        }
      ],
      "_components": [
        {
          "__type__": "cc.Sprite",
          "_name": "barRes<Sprite>",
          "node": {
            "__id__": 5
          },
          "_materials": [
            {
              "__uuid__": "ecpdLyjvZBwrvm+cedCcQy"
            }
          ],
          "_spriteFrame": {
            "__uuid__": "d2mXW5kGNBgIDYxafxddpl"
          },
          "_type": 1,
          "_sizeMode": 0
        },
        {
          "__id__": 9
        }
      ],
      "_prefab": {
        "__type__": "cc.PrefabInfo",
        "root": {
          "__id__": 1
        },
        "asset": {
          "__uuid__": "64jiExftZFbarLd0gJWROg"
        },
        "fileId": "447+CpifJOkLDQa6ugbCT3"
      },
      "_contentSize": {
        "__type__": "cc.Size",
        "width": 306,
        "height": 45
      },
      "_trs": {
        "__type__": "TypedArray",
        "ctor": "Float64Array",
        "array": [
          0,
          23.285,
          0,
          0,
          0,
          0,
          1,
          1,
          1,
          1
        ]
      }
    },
    {
      "__type__": "cc.Node",
      "_name": "spBar",
      "_parent": {
        "__id__": 5
      },
      "_children": [
        {
          "__id__": 7
        }
      ],
      "_components": [
        {
          "__type__": "cc.Sprite",
          "_name": "bar<Sprite>",
          "node": {
            "__id__": 6
          },
          "_materials": [
            {
              "__uuid__": "ecpdLyjvZBwrvm+cedCcQy"
            }
          ],
          "_spriteFrame": {
            "__uuid__": "79/IW/SBhB7LPWbrCNdpnq"
          },
          "_type": 1,
          "_sizeMode": 0
        },
        {
          "__type__": "cc.Layout",
          "node": {
            "__id__": 6
          },
          "_layoutSize": {
            "__type__": "cc.Size",
            "width": 24,
            "height": 25
          },
          "_resize": 1,
          "_N$layoutType": 1,
          "_N$paddingLeft": 12,
          "_N$paddingRight": 12
        }
      ],
      "_prefab": {
        "__type__": "cc.PrefabInfo",
        "root": {
          "__id__": 1
        },
        "asset": {
          "__uuid__": "64jiExftZFbarLd0gJWROg"
        },
        "fileId": "2cGPwI/qFCuYkYCP/4mK3v"
      },
      "_contentSize": {
        "__type__": "cc.Size",
        "width": 24,
        "height": 25
      },
      "_anchorPoint": {
        "__type__": "cc.Vec2",
        "y": 0.5
      },
      "_trs": {
        "__type__": "TypedArray",
        "ctor": "Float64Array",
        "array": [
          -143.043,
          0,
          0,
          0,
          0,
          0,
          1,
          1,
          1,
          1
        ]
      }
    },
    {
      "__type__": "cc.Node",
      "_name": "spNull",
      "_parent": {
        "__id__": 6
      },
      "_components": [
        {
          "__id__": 8
        }
      ],
      "_prefab": {
        "__type__": "cc.PrefabInfo",
        "root": {
          "__id__": 1
        },
        "asset": {
          "__uuid__": "64jiExftZFbarLd0gJWROg"
        },
        "fileId": "ccXn48Nj1F9oeOGM3cjA5L"
      },
      "_contentSize": {
        "__type__": "cc.Size",
        "height": 3
      },
      "_anchorPoint": {
        "__type__": "cc.Vec2",
        "y": 0.5
      },
      "_trs": {
        "__type__": "TypedArray",
        "ctor": "Float64Array",
        "array": [
          12,
          0,
          0,
          0,
          0,
          0,
          1,
          1,
          1,
          1
        ]
      }
    },
    {
      "__type__": "cc.Sprite",
      "node": {
        "__id__": 7
      },
      "_materials": [
        {
          "__uuid__": "ecpdLyjvZBwrvm+cedCcQy"
        }
      ],
      "_spriteFrame": {
        "__uuid__": "e6R/4R5eZKmroe0wI8FCD2"
      },
      "_type": 1,
      "_sizeMode": 0
    },
    {
      "__type__": "cc.ProgressBar",
      "node": {
        "__id__": 5
      },
      "_N$totalLength": 262,
      "_N$barSprite": {
        "__id__": 8
      },
      "_N$progress": 0
    }
  ],
  {
    "__type__": "cc.SpriteFrame",
    "content": {
      "name": "cm_loadbar",
      "texture": "a1txpicYpPqaFEn1KTjSoE",
      "rect": [
        1,
        451,
        286,
        25
      ],
      "offset": [
        0,
        0
      ],
      "originalSize": [
        306,
        45
      ],
      "capInsets": [
        11,
        7,
        11,
        7
      ]
    }
  },
  {
    "__type__": "cc.SpriteFrame",
    "content": {
      "name": "default_sprite_splash",
      "texture": "02delMVqdBD70a/HSD99FK",
      "rect": [
        0,
        0,
        2,
        2
      ],
      "offset": [
        0,
        0
      ],
      "originalSize": [
        2,
        2
      ],
      "capInsets": [
        0,
        0,
        0,
        0
      ]
    }
  },
  {
    "__type__": "cc.SpriteFrame",
    "content": {
      "name": "cm_loadbar_bg",
      "texture": "a1txpicYpPqaFEn1KTjSoE",
      "rect": [
        459,
        10,
        306,
        45
      ],
      "offset": [
        0,
        0
      ],
      "originalSize": [
        306,
        45
      ],
      "capInsets": [
        0,
        0,
        0,
        0
      ]
    }
  },
  {
    "__type__": "cc.SpriteFrame",
    "content": {
      "name": "cm_null",
      "texture": "a1txpicYpPqaFEn1KTjSoE",
      "rect": [
        731,
        420,
        3,
        3
      ],
      "offset": [
        -0.5,
        0.5
      ],
      "originalSize": [
        4,
        4
      ],
      "capInsets": [
        0,
        0,
        0,
        0
      ]
    }
  }
]