[
  {
    "__type__": "cc.SpriteFrame",
    "content": {
      "name": "lp_vx_btn",
      "texture": "a9Yk08i5JChIz2hVBuo8Js",
      "rect": [
        0,
        0,
        226,
        81
      ],
      "offset": [
        0,
        0
      ],
      "originalSize": [
        226,
        81
      ],
      "capInsets": [
        0,
        0,
        0,
        0
      ]
    }
  },
  {
    "__type__": "cc.SpriteFrame",
    "content": {
      "name": "lp_login_txt",
      "texture": "557ILJYB1FuosYU7ZebEAK",
      "rect": [
        0,
        0,
        63,
        29
      ],
      "offset": [
        0,
        0
      ],
      "originalSize": [
        63,
        29
      ],
      "capInsets": [
        0,
        0,
        0,
        0
      ]
    }
  },
  [
    {
      "__type__": "cc.SceneAsset",
      "_name": "LoginScene",
      "scene": {
        "__id__": 1
      },
      "asyncLoadAssets": null
    },
    {
      "__type__": "cc.Scene",
      "_name": "New Node",
      "_children": [
        {
          "__id__": 2
        }
      ],
      "_active": false,
      "_anchorPoint": {
        "__type__": "cc.Vec2"
      },
      "_trs": {
        "__type__": "TypedArray",
        "ctor": "Float64Array",
        "array": [
          0,
          0,
          0,
          0,
          0,
          0,
          1,
          1,
          1,
          1
        ]
      },
      "autoReleaseAssets": false
    },
    {
      "__type__": "cc.Node",
      "_name": "Canvas",
      "_parent": {
        "__id__": 1
      },
      "_children": [
        {
          "__id__": 3
        },
        {
          "__id__": 4
        },
        {
          "__id__": 6
        },
        {
          "__id__": 10
        },
        {
          "__id__": 17
        },
        {
          "__id__": 19
        },
        {
          "__id__": 21
        }
      ],
      "_components": [
        {
          "__type__": "cc.Canvas",
          "node": {
            "__id__": 2
          },
          "_designResolution": {
            "__type__": "cc.Size",
            "width": 1366,
            "height": 768
          }
        },
        {
          "__type__": "cc.Widget",
          "node": {
            "__id__": 2
          },
          "_alignFlags": 45
        },
        {
          "__type__": "d7755BGYXBPdZRn0oqkFN7Y",
          "node": {
            "__id__": 2
          },
          "nodeBg": {
            "__id__": 4
          },
          "btnTokenLogin": {
            "__id__": 17
          },
          "btnVisitorLogin": {
            "__id__": 7
          },
          "btnWXLogin": {
            "__id__": 8
          },
          "btnPhoneLogin": {
            "__id__": 9
          },
          "nodeLoginWay": {
            "__id__": 6
          },
          "togAgreement": {
            "__id__": 15
          },
          "btnAgreement": {
            "__id__": 16
          },
          "nodeTestNet": {
            "__id__": 21
          }
        }
      ],
      "_contentSize": {
        "__type__": "cc.Size",
        "width": 1366,
        "height": 768
      },
      "_trs": {
        "__type__": "TypedArray",
        "ctor": "Float64Array",
        "array": [
          683,
          384,
          0,
          0,
          0,
          0,
          1,
          1,
          1,
          1
        ]
      },
      "_id": "a5esZu+45LA5mBpvttspPD"
    },
    {
      "__type__": "cc.Node",
      "_name": "Main Camera",
      "_parent": {
        "__id__": 2
      },
      "_components": [
        {
          "__type__": "cc.Camera",
          "node": {
            "__id__": 3
          },
          "_clearFlags": 7,
          "_depth": -1
        }
      ],
      "_trs": {
        "__type__": "TypedArray",
        "ctor": "Float64Array",
        "array": [
          0,
          0,
          533.4526396217241,
          0,
          0,
          0,
          1,
          1,
          1,
          1
        ]
      }
    },
    {
      "__type__": "cc.Node",
      "_name": "spBodybg",
      "_parent": {
        "__id__": 2
      },
      "_children": [
        {
          "__id__": 5
        }
      ],
      "_components": [
        {
          "__type__": "cc.Sprite",
          "node": {
            "__id__": 4
          },
          "_materials": [
            {
              "__uuid__": "ecpdLyjvZBwrvm+cedCcQy"
            }
          ],
          "_spriteFrame": {
            "__uuid__": "f682Tf8dlK+aqyu9CHF3jX"
          },
          "_sizeMode": 0
        },
        {
          "__type__": "cc.Widget",
          "node": {
            "__id__": 4
          },
          "_alignFlags": 45,
          "_originalWidth": 40,
          "_originalHeight": 36
        }
      ],
      "_contentSize": {
        "__type__": "cc.Size",
        "width": 1366,
        "height": 768
      },
      "_trs": {
        "__type__": "TypedArray",
        "ctor": "Float64Array",
        "array": [
          0,
          0,
          0,
          0,
          0,
          0,
          1,
          1,
          1,
          1
        ]
      }
    },
    {
      "__type__": "cc.Node",
      "_name": "spLogo",
      "_parent": {
        "__id__": 4
      },
      "_components": [
        {
          "__type__": "cc.Sprite",
          "node": {
            "__id__": 5
          },
          "_materials": [
            {
              "__uuid__": "ecpdLyjvZBwrvm+cedCcQy"
            }
          ],
          "_spriteFrame": {
            "__uuid__": "7anHF6201J17VDHWF3LMHP"
          }
        }
      ],
      "_contentSize": {
        "__type__": "cc.Size",
        "width": 792,
        "height": 494
      },
      "_trs": {
        "__type__": "TypedArray",
        "ctor": "Float64Array",
        "array": [
          0.824,
          148.774,
          0,
          0,
          0,
          0,
          1,
          0.7,
          0.7,
          1
        ]
      }
    },
    {
      "__type__": "cc.Node",
      "_name": "nodeLoginWay",
      "_parent": {
        "__id__": 2
      },
      "_children": [
        {
          "__id__": 7
        },
        {
          "__id__": 8
        },
        {
          "__id__": 9
        }
      ],
      "_active": false,
      "_components": [
        {
          "__type__": "cc.Layout",
          "node": {
            "__id__": 6
          },
          "_layoutSize": {
            "__type__": "cc.Size",
            "width": 808,
            "height": 100
          },
          "_resize": 1,
          "_N$layoutType": 1,
          "_N$spacingX": 65
        },
        {
          "__type__": "cc.Widget",
          "node": {
            "__id__": 6
          },
          "_alignFlags": 16
        }
      ],
      "_contentSize": {
        "__type__": "cc.Size",
        "width": 808,
        "height": 100
      },
      "_trs": {
        "__type__": "TypedArray",
        "ctor": "Float64Array",
        "array": [
          0,
          -103.582,
          0,
          0,
          0,
          0,
          1,
          1,
          1,
          1
        ]
      }
    },
    {
      "__type__": "cc.Node",
      "_name": "btnVisitorLogin",
      "_parent": {
        "__id__": 6
      },
      "_components": [
        {
          "__type__": "cc.Sprite",
          "node": {
            "__id__": 7
          },
          "_materials": [
            {
              "__uuid__": "ecpdLyjvZBwrvm+cedCcQy"
            }
          ],
          "_spriteFrame": {
            "__uuid__": "696O9Y3QlBDIRnwOR2cJyT"
          }
        },
        {
          "__type__": "cc.Button",
          "node": {
            "__id__": 7
          },
          "_normalMaterial": {
            "__uuid__": "ecpdLyjvZBwrvm+cedCcQy"
          },
          "zoomScale": 0.97,
          "_N$transition": 3,
          "transition": 3
        }
      ],
      "_contentSize": {
        "__type__": "cc.Size",
        "width": 226,
        "height": 81
      },
      "_trs": {
        "__type__": "TypedArray",
        "ctor": "Float64Array",
        "array": [
          -291,
          -5.764,
          0,
          0,
          0,
          0,
          1,
          1,
          1,
          1
        ]
      }
    },
    {
      "__type__": "cc.Node",
      "_name": "btnVXLogin",
      "_parent": {
        "__id__": 6
      },
      "_components": [
        {
          "__type__": "cc.Sprite",
          "node": {
            "__id__": 8
          },
          "_materials": [
            {
              "__uuid__": "ecpdLyjvZBwrvm+cedCcQy"
            }
          ],
          "_spriteFrame": {
            "__uuid__": "1cryV8XJlAIrPd/wkx6vhc"
          }
        },
        {
          "__type__": "cc.Button",
          "node": {
            "__id__": 8
          },
          "_normalMaterial": {
            "__uuid__": "ecpdLyjvZBwrvm+cedCcQy"
          },
          "zoomScale": 0.97,
          "_N$transition": 3,
          "transition": 3
        }
      ],
      "_contentSize": {
        "__type__": "cc.Size",
        "width": 226,
        "height": 81
      },
      "_trs": {
        "__type__": "TypedArray",
        "ctor": "Float64Array",
        "array": [
          0,
          -5.764,
          0,
          0,
          0,
          0,
          1,
          1,
          1,
          1
        ]
      }
    },
    {
      "__type__": "cc.Node",
      "_name": "btnPhoneLogin",
      "_parent": {
        "__id__": 6
      },
      "_components": [
        {
          "__type__": "cc.Sprite",
          "node": {
            "__id__": 9
          },
          "_materials": [
            {
              "__uuid__": "ecpdLyjvZBwrvm+cedCcQy"
            }
          ],
          "_spriteFrame": {
            "__uuid__": "8azmoZcLZI3K6uCgD1IjI1"
          }
        },
        {
          "__type__": "cc.Button",
          "node": {
            "__id__": 9
          },
          "_normalMaterial": {
            "__uuid__": "ecpdLyjvZBwrvm+cedCcQy"
          },
          "zoomScale": 0.97,
          "_N$transition": 3,
          "transition": 3
        }
      ],
      "_contentSize": {
        "__type__": "cc.Size",
        "width": 226,
        "height": 81
      },
      "_trs": {
        "__type__": "TypedArray",
        "ctor": "Float64Array",
        "array": [
          291,
          -5.764,
          0,
          0,
          0,
          0,
          1,
          1,
          1,
          1
        ]
      }
    },
    {
      "__type__": "cc.Node",
      "_name": "nodeAgreement",
      "_parent": {
        "__id__": 2
      },
      "_children": [
        {
          "__id__": 11
        },
        {
          "__id__": 16
        }
      ],
      "_contentSize": {
        "__type__": "cc.Size",
        "width": 250.8,
        "height": 40
      },
      "_trs": {
        "__type__": "TypedArray",
        "ctor": "Float64Array",
        "array": [
          0,
          -205.47,
          0,
          0,
          0,
          0,
          1,
          1,
          1,
          1
        ]
      }
    },
    {
      "__type__": "cc.Node",
      "_name": "togAgreement",
      "_parent": {
        "__id__": 10
      },
      "_children": [
        {
          "__id__": 12
        },
        {
          "__id__": 13
        }
      ],
      "_components": [
        {
          "__id__": 15
        }
      ],
      "_contentSize": {
        "__type__": "cc.Size",
        "width": 28,
        "height": 28
      },
      "_trs": {
        "__type__": "TypedArray",
        "ctor": "Float64Array",
        "array": [
          -96.073,
          0,
          0,
          0,
          0,
          0,
          1,
          1,
          1,
          1
        ]
      }
    },
    {
      "__type__": "cc.Node",
      "_name": "Background",
      "_parent": {
        "__id__": 11
      },
      "_components": [
        {
          "__type__": "cc.Sprite",
          "node": {
            "__id__": 12
          },
          "_materials": [
            {
              "__uuid__": "ecpdLyjvZBwrvm+cedCcQy"
            }
          ],
          "_spriteFrame": {
            "__uuid__": "a11x7fDuBJO7rlVt2hRLNJ"
          }
        }
      ],
      "_contentSize": {
        "__type__": "cc.Size",
        "width": 38,
        "height": 38
      },
      "_trs": {
        "__type__": "TypedArray",
        "ctor": "Float64Array",
        "array": [
          0,
          0,
          0,
          0,
          0,
          0,
          1,
          1,
          1,
          1
        ]
      }
    },
    {
      "__type__": "cc.Node",
      "_name": "checkmark",
      "_parent": {
        "__id__": 11
      },
      "_components": [
        {
          "__id__": 14
        }
      ],
      "_contentSize": {
        "__type__": "cc.Size",
        "width": 39,
        "height": 38
      },
      "_trs": {
        "__type__": "TypedArray",
        "ctor": "Float64Array",
        "array": [
          0,
          0,
          0,
          0,
          0,
          0,
          1,
          1,
          1,
          1
        ]
      }
    },
    {
      "__type__": "cc.Sprite",
      "node": {
        "__id__": 13
      },
      "_materials": [
        {
          "__uuid__": "ecpdLyjvZBwrvm+cedCcQy"
        }
      ],
      "_spriteFrame": {
        "__uuid__": "6b4As8MstKz6cEh+3KAaxY"
      },
      "_sizeMode": 2,
      "_isTrimmedMode": false
    },
    {
      "__type__": "cc.Toggle",
      "node": {
        "__id__": 11
      },
      "_normalMaterial": {
        "__uuid__": "ecpdLyjvZBwrvm+cedCcQy"
      },
      "zoomScale": 0.97,
      "_N$transition": 3,
      "transition": 3,
      "_N$normalColor": {
        "__type__": "cc.Color",
        "r": 214,
        "g": 214,
        "b": 214
      },
      "_N$target": {
        "__id__": 12
      },
      "checkMark": {
        "__id__": 14
      }
    },
    {
      "__type__": "cc.Node",
      "_name": "btnAgreement",
      "_parent": {
        "__id__": 10
      },
      "_components": [
        {
          "__type__": "cc.Label",
          "node": {
            "__id__": 16
          },
          "_materials": [
            {
              "__uuid__": "ecpdLyjvZBwrvm+cedCcQy"
            }
          ],
          "_useOriginalSize": false,
          "_string": "同意用户协议",
          "_N$string": "同意用户协议",
          "_fontSize": 30,
          "_lineHeight": 32,
          "_N$file": {
            "__uuid__": "bcogdoz1tLfbeyAkU44/DX"
          },
          "_isSystemFontUsed": false,
          "_styleFlags": 4,
          "_N$horizontalAlign": 1,
          "_N$verticalAlign": 1
        },
        {
          "__type__": "cc.Button",
          "node": {
            "__id__": 16
          },
          "zoomScale": 0.97,
          "_N$transition": 3,
          "transition": 3
        }
      ],
      "_color": {
        "__type__": "cc.Color",
        "r": 82,
        "g": 68,
        "b": 85
      },
      "_contentSize": {
        "__type__": "cc.Size",
        "width": 180,
        "height": 40.32
      },
      "_trs": {
        "__type__": "TypedArray",
        "ctor": "Float64Array",
        "array": [
          19.942,
          0,
          0,
          0,
          0,
          0,
          1,
          1,
          1,
          1
        ]
      }
    },
    {
      "__type__": "cc.Node",
      "_name": "btnTokenLogin",
      "_parent": {
        "__id__": 2
      },
      "_children": [
        {
          "__id__": 18
        }
      ],
      "_components": [
        {
          "__type__": "cc.Sprite",
          "node": {
            "__id__": 17
          },
          "_materials": [
            {
              "__uuid__": "ecpdLyjvZBwrvm+cedCcQy"
            }
          ],
          "_spriteFrame": {
            "__uuid__": "b3JuZ3MUFEgrOd4bC44ZkZ"
          }
        },
        {
          "__type__": "cc.Button",
          "node": {
            "__id__": 17
          },
          "_normalMaterial": {
            "__uuid__": "ecpdLyjvZBwrvm+cedCcQy"
          },
          "zoomScale": 0.97,
          "_N$transition": 3,
          "transition": 3
        }
      ],
      "_contentSize": {
        "__type__": "cc.Size",
        "width": 178,
        "height": 62
      },
      "_trs": {
        "__type__": "TypedArray",
        "ctor": "Float64Array",
        "array": [
          0,
          -98.273,
          0,
          0,
          0,
          0,
          1,
          1,
          1,
          1
        ]
      }
    },
    {
      "__type__": "cc.Node",
      "_name": "spLogintxt",
      "_parent": {
        "__id__": 17
      },
      "_components": [
        {
          "__type__": "cc.Sprite",
          "node": {
            "__id__": 18
          },
          "_materials": [
            {
              "__uuid__": "ecpdLyjvZBwrvm+cedCcQy"
            }
          ],
          "_spriteFrame": {
            "__uuid__": "30vB88iKBMdLvfDtuZLd1J"
          }
        }
      ],
      "_contentSize": {
        "__type__": "cc.Size",
        "width": 63,
        "height": 29
      },
      "_trs": {
        "__type__": "TypedArray",
        "ctor": "Float64Array",
        "array": [
          0,
          0,
          0,
          0,
          0,
          0,
          1,
          1,
          1,
          1
        ]
      }
    },
    {
      "__type__": "cc.Node",
      "_name": "nodeBottom",
      "_parent": {
        "__id__": 2
      },
      "_children": [
        {
          "__id__": 20
        }
      ],
      "_components": [
        {
          "__type__": "cc.Widget",
          "node": {
            "__id__": 19
          },
          "_alignFlags": 4
        },
        {
          "__type__": "cc.Sprite",
          "node": {
            "__id__": 19
          },
          "_materials": [
            {
              "__uuid__": "ecpdLyjvZBwrvm+cedCcQy"
            }
          ],
          "_spriteFrame": {
            "__uuid__": "9eXkASea5I85C8gZ8f59ez"
          },
          "_type": 1,
          "_sizeMode": 0
        }
      ],
      "_contentSize": {
        "__type__": "cc.Size",
        "width": 1366,
        "height": 100
      },
      "_trs": {
        "__type__": "TypedArray",
        "ctor": "Float64Array",
        "array": [
          0,
          -334,
          0,
          0,
          0,
          0,
          1,
          1,
          1,
          1
        ]
      }
    },
    {
      "__type__": "cc.Node",
      "_name": "lbBottom",
      "_parent": {
        "__id__": 19
      },
      "_components": [
        {
          "__type__": "cc.Label",
          "node": {
            "__id__": 20
          },
          "_materials": [
            {
              "__uuid__": "ecpdLyjvZBwrvm+cedCcQy"
            }
          ],
          "_useOriginalSize": false,
          "_string": "健康游戏忠告：抵制不良游戏 拒绝盗版游戏 注意自我保护 谨防受骗上当 适度游戏益脑 沉迷游戏伤身 合理安排时间 分享健康生活\n备案号：文网游备字[2018]M-CBG 0541号             文网文：沪网文[2016]3915-285号            批准文号：新广出审[2018]219号  \n出版物号：ISBN 978-7-498-03658-2    著作权人：上海时珩网络科技有限公司     出版服务单位：成都盈众九州网络科技有限公司",
          "_N$string": "健康游戏忠告：抵制不良游戏 拒绝盗版游戏 注意自我保护 谨防受骗上当 适度游戏益脑 沉迷游戏伤身 合理安排时间 分享健康生活\n备案号：文网游备字[2018]M-CBG 0541号             文网文：沪网文[2016]3915-285号            批准文号：新广出审[2018]219号  \n出版物号：ISBN 978-7-498-03658-2    著作权人：上海时珩网络科技有限公司     出版服务单位：成都盈众九州网络科技有限公司",
          "_fontSize": 20,
          "_lineHeight": 22,
          "_N$file": {
            "__uuid__": "bcogdoz1tLfbeyAkU44/DX"
          },
          "_isSystemFontUsed": false,
          "_N$horizontalAlign": 1,
          "_N$verticalAlign": 1
        },
        {
          "__type__": "cc.Widget",
          "node": {
            "__id__": 20
          },
          "_alignFlags": 16
        }
      ],
      "_contentSize": {
        "__type__": "cc.Size",
        "width": 1135,
        "height": 71.72
      },
      "_trs": {
        "__type__": "TypedArray",
        "ctor": "Float64Array",
        "array": [
          0,
          0,
          0,
          0,
          0,
          0,
          1,
          1,
          1,
          1
        ]
      }
    },
    {
      "__type__": "cc.Node",
      "_name": "nodeTestNet",
      "_parent": {
        "__id__": 2
      },
      "_children": [
        {
          "__id__": 22
        },
        {
          "__id__": 24
        }
      ],
      "_active": false,
      "_components": [
        {
          "__type__": "cc.BlockInputEvents",
          "node": {
            "__id__": 21
          }
        }
      ],
      "_contentSize": {
        "__type__": "cc.Size",
        "width": 1366,
        "height": 768
      },
      "_trs": {
        "__type__": "TypedArray",
        "ctor": "Float64Array",
        "array": [
          0,
          0,
          0,
          0,
          0,
          0,
          1,
          1,
          1,
          1
        ]
      }
    },
    {
      "__type__": "cc.Node",
      "_name": "spBodybg",
      "_parent": {
        "__id__": 21
      },
      "_children": [
        {
          "__id__": 23
        }
      ],
      "_components": [
        {
          "__type__": "cc.Sprite",
          "node": {
            "__id__": 22
          },
          "_materials": [
            {
              "__uuid__": "ecpdLyjvZBwrvm+cedCcQy"
            }
          ],
          "_spriteFrame": {
            "__uuid__": "f682Tf8dlK+aqyu9CHF3jX"
          },
          "_sizeMode": 0
        },
        {
          "__type__": "cc.Widget",
          "node": {
            "__id__": 22
          },
          "_alignFlags": 45,
          "_originalWidth": 40,
          "_originalHeight": 36
        }
      ],
      "_contentSize": {
        "__type__": "cc.Size",
        "width": 1366,
        "height": 768
      },
      "_trs": {
        "__type__": "TypedArray",
        "ctor": "Float64Array",
        "array": [
          0,
          0,
          0,
          0,
          0,
          0,
          1,
          1,
          1,
          1
        ]
      }
    },
    {
      "__type__": "cc.Node",
      "_name": "spLogo",
      "_parent": {
        "__id__": 22
      },
      "_components": [
        {
          "__type__": "cc.Sprite",
          "node": {
            "__id__": 23
          },
          "_materials": [
            {
              "__uuid__": "ecpdLyjvZBwrvm+cedCcQy"
            }
          ],
          "_spriteFrame": {
            "__uuid__": "7anHF6201J17VDHWF3LMHP"
          }
        }
      ],
      "_contentSize": {
        "__type__": "cc.Size",
        "width": 792,
        "height": 494
      },
      "_trs": {
        "__type__": "TypedArray",
        "ctor": "Float64Array",
        "array": [
          0.824,
          148.774,
          0,
          0,
          0,
          0,
          1,
          0.7,
          0.7,
          1
        ]
      }
    },
    {
      "__type__": "cc.Node",
      "_name": "nodeNetGroup",
      "_parent": {
        "__id__": 21
      },
      "_children": [
        {
          "__id__": 25
        },
        {
          "__id__": 27
        }
      ],
      "_components": [
        {
          "__type__": "cc.Layout",
          "node": {
            "__id__": 24
          },
          "_layoutSize": {
            "__type__": "cc.Size",
            "width": 350,
            "height": 80
          },
          "_resize": 1,
          "_N$layoutType": 1,
          "_N$spacingX": 50
        },
        {
          "__type__": "cc.Widget",
          "node": {
            "__id__": 24
          },
          "_alignFlags": 18,
          "_verticalCenter": -180
        }
      ],
      "_contentSize": {
        "__type__": "cc.Size",
        "width": 350,
        "height": 80
      },
      "_trs": {
        "__type__": "TypedArray",
        "ctor": "Float64Array",
        "array": [
          0,
          -180,
          0,
          0,
          0,
          0,
          1,
          1,
          1,
          1
        ]
      }
    },
    {
      "__type__": "cc.Node",
      "_name": "nodeNetWork",
      "_parent": {
        "__id__": 24
      },
      "_children": [
        {
          "__id__": 26
        }
      ],
      "_components": [
        {
          "__type__": "cc.Sprite",
          "node": {
            "__id__": 25
          },
          "_materials": [
            {
              "__uuid__": "ecpdLyjvZBwrvm+cedCcQy"
            }
          ],
          "_spriteFrame": {
            "__uuid__": "68G33Ln9NF1KTKIYN0IOVr"
          },
          "_type": 1,
          "_sizeMode": 0
        },
        {
          "__type__": "cc.Button",
          "node": {
            "__id__": 25
          },
          "_normalMaterial": {
            "__uuid__": "ecpdLyjvZBwrvm+cedCcQy"
          },
          "_grayMaterial": {
            "__uuid__": "3ae7efMv1CLq2ilvUY/tQi"
          },
          "zoomScale": 0.97,
          "clickEvents": [
            {
              "__type__": "cc.ClickEvent",
              "target": {
                "__id__": 2
              },
              "_componentId": "d7755BGYXBPdZRn0oqkFN7Y",
              "handler": "onTestClick",
              "customEventData": "lm_work"
            }
          ],
          "_N$transition": 3,
          "transition": 3
        }
      ],
      "_contentSize": {
        "__type__": "cc.Size",
        "width": 150,
        "height": 80
      },
      "_trs": {
        "__type__": "TypedArray",
        "ctor": "Float64Array",
        "array": [
          -100,
          0,
          0,
          0,
          0,
          0,
          1,
          1,
          1,
          1
        ]
      }
    },
    {
      "__type__": "cc.Node",
      "_name": "lbIP",
      "_parent": {
        "__id__": 25
      },
      "_components": [
        {
          "__type__": "cc.Label",
          "node": {
            "__id__": 26
          },
          "_materials": [
            {
              "__uuid__": "ecpdLyjvZBwrvm+cedCcQy"
            }
          ],
          "_useOriginalSize": false,
          "_string": "开发-20",
          "_N$string": "开发-20",
          "_fontSize": 28,
          "_lineHeight": 30,
          "_N$file": {
            "__uuid__": "bcogdoz1tLfbeyAkU44/DX"
          },
          "_isSystemFontUsed": false,
          "_N$horizontalAlign": 1,
          "_N$verticalAlign": 1
        }
      ],
      "_color": {
        "__type__": "cc.Color"
      },
      "_contentSize": {
        "__type__": "cc.Size",
        "width": 102.7,
        "height": 37.8
      },
      "_trs": {
        "__type__": "TypedArray",
        "ctor": "Float64Array",
        "array": [
          0,
          0,
          0,
          0,
          0,
          0,
          1,
          1,
          1,
          1
        ]
      }
    },
    {
      "__type__": "cc.Node",
      "_name": "nodeNetTest",
      "_parent": {
        "__id__": 24
      },
      "_children": [
        {
          "__id__": 28
        }
      ],
      "_components": [
        {
          "__type__": "cc.Sprite",
          "node": {
            "__id__": 27
          },
          "_materials": [
            {
              "__uuid__": "ecpdLyjvZBwrvm+cedCcQy"
            }
          ],
          "_spriteFrame": {
            "__uuid__": "68G33Ln9NF1KTKIYN0IOVr"
          },
          "_type": 1,
          "_sizeMode": 0
        },
        {
          "__type__": "cc.Button",
          "node": {
            "__id__": 27
          },
          "_normalMaterial": {
            "__uuid__": "ecpdLyjvZBwrvm+cedCcQy"
          },
          "_grayMaterial": {
            "__uuid__": "3ae7efMv1CLq2ilvUY/tQi"
          },
          "zoomScale": 0.97,
          "clickEvents": [
            {
              "__type__": "cc.ClickEvent",
              "target": {
                "__id__": 2
              },
              "_componentId": "d7755BGYXBPdZRn0oqkFN7Y",
              "handler": "onTestClick",
              "customEventData": "lm_test"
            }
          ],
          "_N$transition": 3,
          "transition": 3
        }
      ],
      "_contentSize": {
        "__type__": "cc.Size",
        "width": 150,
        "height": 80
      },
      "_trs": {
        "__type__": "TypedArray",
        "ctor": "Float64Array",
        "array": [
          100,
          0,
          0,
          0,
          0,
          0,
          1,
          1,
          1,
          1
        ]
      }
    },
    {
      "__type__": "cc.Node",
      "_name": "lbIP",
      "_parent": {
        "__id__": 27
      },
      "_components": [
        {
          "__type__": "cc.Label",
          "node": {
            "__id__": 28
          },
          "_materials": [
            {
              "__uuid__": "ecpdLyjvZBwrvm+cedCcQy"
            }
          ],
          "_useOriginalSize": false,
          "_string": " 测试-100",
          "_N$string": " 测试-100",
          "_fontSize": 28,
          "_lineHeight": 30,
          "_N$horizontalAlign": 1,
          "_N$verticalAlign": 1
        }
      ],
      "_color": {
        "__type__": "cc.Color"
      },
      "_contentSize": {
        "__type__": "cc.Size",
        "width": 119.82,
        "height": 37.8
      },
      "_trs": {
        "__type__": "TypedArray",
        "ctor": "Float64Array",
        "array": [
          0,
          0,
          0,
          0,
          0,
          0,
          1,
          1,
          1,
          1
        ]
      }
    }
  ],
  {
    "__type__": "cc.SpriteFrame",
    "content": {
      "name": "cm_ctn_bg",
      "texture": "0cZyURBVJGjK9LuSFktPhA",
      "rect": [
        0,
        0,
        40,
        40
      ],
      "offset": [
        0,
        0
      ],
      "originalSize": [
        40,
        40
      ],
      "capInsets": [
        18,
        19,
        18,
        19
      ]
    }
  },
  {
    "__type__": "cc.SpriteFrame",
    "content": {
      "name": "lp_visitor_btn",
      "texture": "d2YTaI1gRFgYmlF3Xk5lvk",
      "rect": [
        0,
        0,
        226,
        81
      ],
      "offset": [
        0,
        0
      ],
      "originalSize": [
        226,
        81
      ],
      "capInsets": [
        0,
        0,
        0,
        0
      ]
    }
  },
  {
    "__type__": "cc.SpriteFrame",
    "content": {
      "name": "lp_toggle_ok_btn",
      "texture": "3aOHLa7BRJaLNEY2+IMtfZ",
      "rect": [
        0,
        0,
        39,
        38
      ],
      "offset": [
        0,
        0
      ],
      "originalSize": [
        39,
        38
      ],
      "capInsets": [
        0,
        0,
        0,
        0
      ]
    }
  },
  {
    "__type__": "cc.SpriteFrame",
    "content": {
      "name": "logo",
      "texture": "eby7SEuy9AG5NQGaRAOtxG",
      "rect": [
        0,
        0,
        792,
        494
      ],
      "offset": [
        0,
        0
      ],
      "originalSize": [
        792,
        494
      ],
      "capInsets": [
        0,
        0,
        0,
        0
      ]
    }
  },
  {
    "__type__": "cc.SpriteFrame",
    "content": {
      "name": "lp_phone_btn",
      "texture": "5b/bMk1FZKy6kyv1dG+2bm",
      "rect": [
        0,
        0,
        226,
        81
      ],
      "offset": [
        0,
        0
      ],
      "originalSize": [
        226,
        81
      ],
      "capInsets": [
        0,
        0,
        0,
        0
      ]
    }
  },
  {
    "__type__": "cc.SpriteFrame",
    "content": {
      "name": "lp_tip_bg",
      "texture": "04g5MN8wFHaLjHbcOaB61d",
      "rect": [
        0,
        0,
        16,
        80
      ],
      "offset": [
        0,
        0
      ],
      "originalSize": [
        16,
        80
      ],
      "capInsets": [
        5,
        27,
        3,
        26
      ]
    }
  },
  {
    "__type__": "cc.SpriteFrame",
    "content": {
      "name": "lp_toggle_no_btn",
      "texture": "aaFdOyGRBNQItbgIEto2+L",
      "rect": [
        0,
        0,
        38,
        38
      ],
      "offset": [
        0,
        0
      ],
      "originalSize": [
        38,
        38
      ],
      "capInsets": [
        0,
        0,
        0,
        0
      ]
    }
  },
  {
    "__type__": "cc.SpriteFrame",
    "content": {
      "name": "cm_btn_bg_yellow",
      "texture": "f4NHTuaVhGpY6fackLq6vd",
      "rect": [
        0,
        0,
        178,
        62
      ],
      "offset": [
        0,
        0
      ],
      "originalSize": [
        178,
        62
      ],
      "capInsets": [
        39,
        15,
        48,
        16
      ]
    }
  },
  {
    "__type__": "cc.SpriteFrame",
    "content": {
      "name": "lp_bg",
      "texture": "331xRphmdMWL2uByk5/uC8",
      "rect": [
        0,
        0,
        1366,
        768
      ],
      "offset": [
        0,
        0
      ],
      "originalSize": [
        1366,
        768
      ],
      "capInsets": [
        0,
        0,
        0,
        0
      ]
    }
  }
]